pybtex/__init__.py
pybtex/__main__.py
pybtex/auxfile.py
pybtex/cmdline.py
pybtex/errors.py
pybtex/exceptions.py
pybtex/io.py
pybtex/kpathsea.py
pybtex/richtext.py
pybtex/scanner.py
pybtex/textutils.py
pybtex/utils.py
pybtex/backends/__init__.py
pybtex/backends/html.py
pybtex/backends/latex.py
pybtex/backends/markdown.py
pybtex/backends/plaintext.py
pybtex/bibtex/__init__.py
pybtex/bibtex/bst.py
pybtex/bibtex/builtins.py
pybtex/bibtex/exceptions.py
pybtex/bibtex/interpreter.py
pybtex/bibtex/names.py
pybtex/bibtex/runner.py
pybtex/bibtex/utils.py
pybtex/charwidths/__init__.py
pybtex/charwidths/make_charwidths.py
pybtex/database/__init__.py
pybtex/database/convert/__init__.py
pybtex/database/convert/__main__.py
pybtex/database/format/__init__.py
pybtex/database/format/__main__.py
pybtex/database/input/__init__.py
pybtex/database/input/bibtex.py
pybtex/database/input/bibtexml.py
pybtex/database/input/bibyaml.py
pybtex/database/output/__init__.py
pybtex/database/output/bibtex.py
pybtex/database/output/bibtexml.py
pybtex/database/output/bibyaml.py
pybtex/markup/__init__.py
pybtex/plugin/__init__.py
pybtex/style/__init__.py
pybtex/style/template.py
pybtex/style/formatting/__init__.py
pybtex/style/formatting/alpha.py
pybtex/style/formatting/plain.py
pybtex/style/formatting/unsrt.py
pybtex/style/formatting/unsrtalpha.py
pybtex/style/labels/__init__.py
pybtex/style/labels/alpha.py
pybtex/style/labels/number.py
pybtex/style/names/__init__.py
pybtex/style/names/lastfirst.py
pybtex/style/names/plain.py
pybtex/style/sorting/__init__.py
pybtex/style/sorting/author_year_title.py
pybtex/style/sorting/none.py
pybtex-0.25.0.dist-info/licenses/COPYING
pybtex-0.25.0.dist-info/METADATA
pybtex-0.25.0.dist-info/WHEEL
pybtex-0.25.0.dist-info/entry_points.txt
pybtex-0.25.0.dist-info/top_level.txt
pybtex-0.25.0.dist-info/zip-safe
pybtex-0.25.0.dist-info/RECORD
