Metadata-Version: 2.4
Name: pybtex
Version: 0.25.0
Summary: A BibTeX-compatible bibliography processor in Python
Home-page: https://pybtex.org/
Author: Andrey Golovizin
Author-email: ag@sologoc.com
License: MIT
Project-URL: Documentation, https://docs.pybtex.org/
Project-URL: Code, https://bitbucket.org/pybtex-devs/pybtex
Project-URL: Issue tracker, https://bitbucket.org/pybtex-devs/pybtex/issues
Platform: platform-independent
Classifier: Development Status :: 4 - Beta
Classifier: Environment :: Console
Classifier: Intended Audience :: End Users/Desktop
Classifier: Operating System :: OS Independent
Classifier: Programming Language :: Python
Classifier: Programming Language :: Python :: 3
Classifier: Topic :: Text Processing :: Markup :: LaTeX
Classifier: Topic :: Text Processing :: Markup :: XML
Classifier: Topic :: Utilities
Requires-Python: >=3.6
License-File: COPYING
Requires-Dist: PyYAML>=3.01
Requires-Dist: latexcodec>=1.0.4
Requires-Dist: importlib_metadata; python_version < "3.10"
Provides-Extra: test
Requires-Dist: pytest; extra == "test"
Provides-Extra: doc
Requires-Dist: sphinx; extra == "doc"
Dynamic: author
Dynamic: author-email
Dynamic: classifier
Dynamic: description
Dynamic: home-page
Dynamic: license
Dynamic: license-file
Dynamic: platform
Dynamic: project-url
Dynamic: provides-extra
Dynamic: requires-dist
Dynamic: requires-python
Dynamic: summary
